okndecide/__init__.py
okndecide/okndecide.py
okndecide-3.0.4.dist-info/LICENSE
okndecide-3.0.4.dist-info/METADATA
okndecide-3.0.4.dist-info/WHEEL
okndecide-3.0.4.dist-info/entry_points.txt
okndecide-3.0.4.dist-info/top_level.txt
okndecide-3.0.4.dist-info/RECORD
